rpi_sx1280/__about__.py
rpi_sx1280/__init__.py
rpi_sx1280/const.py
rpi_sx1280/io.py
rpi_sx1280/sx1280.py
rpi_sx1280-0.0.2.dist-info/METADATA
rpi_sx1280-0.0.2.dist-info/WHEEL
rpi_sx1280-0.0.2.dist-info/licenses/LICENSE
rpi_sx1280-0.0.2.dist-info/RECORD
