Metadata-Version: 2.3
Name: rpi-sx1280
Version: 0.0.2
Summary: Raspberry Pi LoRa library for SX1280
Project-URL: Documentation, https://github.com/enthusiastics-ltd/rpi-sx1280#readme
Project-URL: Issues, https://github.com/enthusiastics-ltd/rpi-sx1280/issues
Project-URL: Source, https://github.com/enthusiastics-ltd/rpi-sx1280
Author-email: "U.N. Owen" <void@some.where>
License-Expression: MIT
License-File: LICENSE
Classifier: Development Status :: 4 - Beta
Classifier: Programming Language :: Python
Classifier: Programming Language :: Python :: 3.8
Classifier: Programming Language :: Python :: 3.9
Classifier: Programming Language :: Python :: 3.10
Classifier: Programming Language :: Python :: 3.11
Classifier: Programming Language :: Python :: 3.12
Classifier: Programming Language :: Python :: Implementation :: CPython
Classifier: Programming Language :: Python :: Implementation :: PyPy
Requires-Python: >=3.8
Requires-Dist: loguru>=0.7.2
Requires-Dist: rpi-gpio>=0.7.1
Requires-Dist: spidev>=3.6
